varnaapi/__init__.py
varnaapi/config-settings-v1.yml
varnaapi/models.py
varnaapi/param.py
varnaapi/settings.py
varnaapi/extensions/__init__.py
varnaapi/extensions/pdb.py
varnaapi-1.2.0.dist-info/LICENSE
varnaapi-1.2.0.dist-info/METADATA
varnaapi-1.2.0.dist-info/WHEEL
varnaapi-1.2.0.dist-info/top_level.txt
varnaapi-1.2.0.dist-info/RECORD
