Metadata-Version: 2.1
Name: varnaapi
Version: 1.2.0
Summary: Python helper for RNA visualization tool VARNA
Author-email: Hua-Ting Yao <hua-ting.yao@polytechnique.edu>
Project-URL: Homepage, https://amibio.gitlabpages.inria.fr/varna-api
Project-URL: Source Code, https://gitlab.inria.fr/amibio/varna-api
Project-URL: VARNA, https://varna.lisn.upsaclay.fr/index.php
Project-URL: Issues, https://github.com/anthonyhtyao/varnaapi/issues
Classifier: Development Status :: 5 - Production/Stable
Classifier: Intended Audience :: Science/Research
Classifier: Intended Audience :: Developers
Classifier: License :: OSI Approved :: GNU General Public License v3 (GPLv3)
Classifier: Programming Language :: Python :: 3
Classifier: Programming Language :: Python :: 3 :: Only
Classifier: Topic :: Scientific/Engineering
Classifier: Operating System :: OS Independent
Requires-Python: >=3.6
License-File: LICENSE
Requires-Dist: colour
Requires-Dist: deprecated
Requires-Dist: pyyaml
Requires-Dist: platformdirs
Requires-Dist: drawsvg ~=2.0
Requires-Dist: svgpathtools
Requires-Dist: ipython
